lampctl/__init__.py
lampctl/__main__.py
lampctl/color/__init__.py
lampctl/color/hsb.py
lampctl/color/rgb.py
lampctl/system/__init__.py
lampctl/system/combined.py
lampctl/system/hue.py
lampctl/test/__init__.py
lampctl/test/test_colors.py
lampctl-0.1.0.dist-info/LICENSE
lampctl-0.1.0.dist-info/METADATA
lampctl-0.1.0.dist-info/WHEEL
lampctl-0.1.0.dist-info/entry_points.txt
lampctl-0.1.0.dist-info/top_level.txt
lampctl-0.1.0.dist-info/RECORD
