Metadata-Version: 2.1
Name: lampctl
Version: 0.1.0
Summary: CLI utility for controlling smart lamps
Project-URL: Homepage, https://github.com/fwcd/lampctl
Project-URL: Repository, https://github.com/fwcd/lampctl
Classifier: Topic :: Utilities
License-File: LICENSE
Requires-Dist: phue <2,>=1.1
